{
  "nodes": {
    "1m": [
      0,
      1,
      2,
      3,
      4,
      5,
      6,
      7,
      8,
      9,
      10,
      11,
      12,
      13
    ],
    "5m": [],
    "15m": [],
    "1h": [],
    "D": [],
    "W": []
  },
  "rich_node_features": [
    "RichNodeFeature(time_minutes=0.0, daily_phase_sin=0.0, daily_phase_cos=1.0, session_position=0.0, time_to_close=29.0, weekend_proximity=0.2857142857142857, absolute_timestamp=1753916400, day_of_week=3, month_phase=1.0, normalized_price=0.2379825, price_delta_1m=0.0018789527385036876, price_delta_5m=0.022601100122967236, price_delta_15m=0.004204073065057823, volatility_window=0.0388337204614887, energy_state=0.0145, contamination_coefficient=0, fisher_regime=0, session_character=0, cross_tf_confluence=1.0, event_type_id=0, timeframe_source=0, liquidity_type=0, fpfvg_gap_size=0.0, fpfvg_interaction_count=0, first_presentation_flag=0.0, pd_array_strength=0.0, structural_importance=0.0, raw_json={'timestamp': '00:00:00', 'price_level': 23798.25, 'movement_type': 'open'})",
    "RichNodeFeature(time_minutes=720.0, daily_phase_sin=1.2246467991473532e-16, daily_phase_cos=-1.0, session_position=24.82758620689655, time_to_close=0, weekend_proximity=0.2857142857142857, absolute_timestamp=1753916400, day_of_week=3, month_phase=1.0, normalized_price=0.23801, price_delta_1m=0.014834364084047452, price_delta_5m=0.0033486617428926937, price_delta_15m=-0.0045279112518949215, volatility_window=0.041304230603701975, energy_state=0.0145, contamination_coefficient=0, fisher_regime=0, session_character=0, cross_tf_confluence=1.0, event_type_id=1, timeframe_source=0, liquidity_type=0, fpfvg_gap_size=0.0, fpfvg_interaction_count=0, first_presentation_flag=0.0, pd_array_strength=0.0, structural_importance=0.0, raw_json={'timestamp': '12:00:00', 'price_level': 23801.0, 'movement_type': 'session_high'})",
    "RichNodeFeature(time_minutes=750.0, daily_phase_sin=-0.13052619222005132, daily_phase_cos=-0.9914448613738105, session_position=25.862068965517242, time_to_close=0, weekend_proximity=0.2857142857142857, absolute_timestamp=1753916400, day_of_week=3, month_phase=1.0, normalized_price=0.237835, price_delta_1m=0.010944726125596379, price_delta_5m=0.0036015790073189676, price_delta_15m=-0.009715472553544649, volatility_window=0.03550941386899211, energy_state=0.0145, contamination_coefficient=0, fisher_regime=0, session_character=0, cross_tf_confluence=1.0, event_type_id=2, timeframe_source=0, liquidity_type=0, fpfvg_gap_size=0.0, fpfvg_interaction_count=0, first_presentation_flag=0.0, pd_array_strength=0.0, structural_importance=0.0, raw_json={'timestamp': '12:30:00', 'price_level': 23783.5, 'movement_type': 'session_low'})",
    "RichNodeFeature(time_minutes=29.0, daily_phase_sin=0.12619896913582976, daily_phase_cos=0.992004949679715, session_position=1.0, time_to_close=0, weekend_proximity=0.2857142857142857, absolute_timestamp=1753916400, day_of_week=3, month_phase=1.0, normalized_price=0.2378875, price_delta_1m=-0.0008360637488314803, price_delta_5m=-0.003784372102874816, price_delta_15m=0.0031585482401724914, volatility_window=0.019842808275399262, energy_state=0.0145, contamination_coefficient=0, fisher_regime=0, session_character=0, cross_tf_confluence=1.0, event_type_id=3, timeframe_source=0, liquidity_type=0, fpfvg_gap_size=0.0, fpfvg_interaction_count=0, first_presentation_flag=0.0, pd_array_strength=0.0, structural_importance=0.0, raw_json={'timestamp': '00:29:00', 'price_level': 23788.75, 'movement_type': 'close'})",
    "RichNodeFeature(time_minutes=0.0, daily_phase_sin=0.0, daily_phase_cos=1.0, session_position=0.0, time_to_close=29.0, weekend_proximity=0.2857142857142857, absolute_timestamp=1753916400, day_of_week=3, month_phase=1.0, normalized_price=0.2379825, price_delta_1m=-0.014309647725900931, price_delta_5m=-0.0004960542552792619, price_delta_15m=0.011425125713363153, volatility_window=0.04275229333448142, energy_state=0.0145, contamination_coefficient=0, fisher_regime=0, session_character=0, cross_tf_confluence=1.0, event_type_id=0, timeframe_source=0, liquidity_type=0, fpfvg_gap_size=0.0, fpfvg_interaction_count=0, first_presentation_flag=0.0, pd_array_strength=0.0, structural_importance=0.0, raw_json={'timestamp': '00:00:00', 'price_level': 23798.25, 'movement_type': 'open'})",
    "RichNodeFeature(time_minutes=720.0, daily_phase_sin=1.2246467991473532e-16, daily_phase_cos=-1.0, session_position=24.82758620689655, time_to_close=0, weekend_proximity=0.2857142857142857, absolute_timestamp=1753916400, day_of_week=3, month_phase=1.0, normalized_price=0.23801, price_delta_1m=-0.008863728308011949, price_delta_5m=-0.0008979320390449112, price_delta_15m=0.0006289769842901909, volatility_window=0.014545414759714922, energy_state=0.0145, contamination_coefficient=0, fisher_regime=0, session_character=0, cross_tf_confluence=1.0, event_type_id=1, timeframe_source=0, liquidity_type=0, fpfvg_gap_size=0.0, fpfvg_interaction_count=0, first_presentation_flag=0.0, pd_array_strength=0.0, structural_importance=0.0, raw_json={'timestamp': '12:00:00', 'price_level': 23801.0, 'movement_type': 'session_high'})",
    "RichNodeFeature(time_minutes=750.0, daily_phase_sin=-0.13052619222005132, daily_phase_cos=-0.9914448613738105, session_position=25.862068965517242, time_to_close=0, weekend_proximity=0.2857142857142857, absolute_timestamp=1753916400, day_of_week=3, month_phase=1.0, normalized_price=0.237835, price_delta_1m=-0.01516366471973239, price_delta_5m=0.005719270907261699, price_delta_15m=-0.001032679053119575, volatility_window=0.027631159488570846, energy_state=0.0145, contamination_coefficient=0, fisher_regime=0, session_character=0, cross_tf_confluence=1.0, event_type_id=2, timeframe_source=0, liquidity_type=0, fpfvg_gap_size=0.0, fpfvg_interaction_count=0, first_presentation_flag=0.0, pd_array_strength=0.0, structural_importance=0.0, raw_json={'timestamp': '12:30:00', 'price_level': 23783.5, 'movement_type': 'session_low'})",
    "RichNodeFeature(time_minutes=29.0, daily_phase_sin=0.12619896913582976, daily_phase_cos=0.992004949679715, session_position=1.0, time_to_close=0, weekend_proximity=0.2857142857142857, absolute_timestamp=1753916400, day_of_week=3, month_phase=1.0, normalized_price=0.2378875, price_delta_1m=-0.0005304823102806529, price_delta_5m=-0.009585876509595928, price_delta_15m=0.008622069924346198, volatility_window=0.017077656401540752, energy_state=0.0145, contamination_coefficient=0, fisher_regime=0, session_character=0, cross_tf_confluence=1.0, event_type_id=3, timeframe_source=0, liquidity_type=0, fpfvg_gap_size=0.0, fpfvg_interaction_count=0, first_presentation_flag=0.0, pd_array_strength=0.0, structural_importance=0.0, raw_json={'timestamp': '00:29:00', 'price_level': 23788.75, 'movement_type': 'close'})",
    "RichNodeFeature(time_minutes=6.0, daily_phase_sin=0.02617694830787315, daily_phase_cos=0.9996573249755573, session_position=0.20689655172413793, time_to_close=23.0, weekend_proximity=0.2857142857142857, absolute_timestamp=1753916400, day_of_week=3, month_phase=1.0, normalized_price=0.2379825, price_delta_1m=0.007612919009061088, price_delta_5m=0.018511654447716634, price_delta_15m=0.012569378906173418, volatility_window=0.010674816523387634, energy_state=0.0145, contamination_coefficient=0, fisher_regime=0, session_character=0, cross_tf_confluence=1.0, event_type_id=4, timeframe_source=0, liquidity_type=0, fpfvg_gap_size=0.0, fpfvg_interaction_count=0, first_presentation_flag=0.0, pd_array_strength=0.0, structural_importance=0.0, raw_json={'timestamp': '00:06:00', 'price': 23798.25, 'action': 'touch', 'context': 'Midnight_FPFVG_formation_premium_high'})",
    "RichNodeFeature(time_minutes=10.0, daily_phase_sin=0.043619387365336, daily_phase_cos=0.9990482215818578, session_position=0.3448275862068966, time_to_close=19.0, weekend_proximity=0.2857142857142857, absolute_timestamp=1753916400, day_of_week=3, month_phase=1.0, normalized_price=0.2379825, price_delta_1m=0.0023225067610236354, price_delta_5m=-0.003784247482488858, price_delta_15m=-0.01593810426704391, volatility_window=0.02092564171034706, energy_state=0.0145, contamination_coefficient=0, fisher_regime=0, session_character=0, cross_tf_confluence=1.0, event_type_id=4, timeframe_source=0, liquidity_type=0, fpfvg_gap_size=0.0, fpfvg_interaction_count=0, first_presentation_flag=0.0, pd_array_strength=0.0, structural_importance=0.0, raw_json={'timestamp': '00:10:00', 'price': 23798.25, 'action': 'touch', 'context': 'Midnight_FPFVG_rebalanced'})",
    "RichNodeFeature(time_minutes=18.0, daily_phase_sin=0.07845909572784494, daily_phase_cos=0.996917333733128, session_position=0.6206896551724138, time_to_close=11.0, weekend_proximity=0.2857142857142857, absolute_timestamp=1753916400, day_of_week=3, month_phase=1.0, normalized_price=0.23791, price_delta_1m=0.002565231187087011, price_delta_5m=0.0020956086914075108, price_delta_15m=-0.00646551386733484, volatility_window=0.028179682532343188, energy_state=0.0145, contamination_coefficient=0, fisher_regime=0, session_character=0, cross_tf_confluence=1.0, event_type_id=4, timeframe_source=0, liquidity_type=0, fpfvg_gap_size=0.0, fpfvg_interaction_count=0, first_presentation_flag=0.0, pd_array_strength=0.0, structural_importance=0.0, raw_json={'timestamp': '00:18:00', 'price': 23791.0, 'action': 'touch', 'context': 'reversal_point_formation'})",
    "RichNodeFeature(time_minutes=22.0, daily_phase_sin=0.09584575252022398, daily_phase_cos=0.9953961983671789, session_position=0.7586206896551724, time_to_close=7.0, weekend_proximity=0.2857142857142857, absolute_timestamp=1753916400, day_of_week=3, month_phase=1.0, normalized_price=0.23801, price_delta_1m=-0.009044432046535086, price_delta_5m=-0.01528793007468466, price_delta_15m=0.023031313516122812, volatility_window=0.01312300882265479, energy_state=0.0145, contamination_coefficient=0, fisher_regime=0, session_character=0, cross_tf_confluence=1.0, event_type_id=4, timeframe_source=0, liquidity_type=0, fpfvg_gap_size=0.0, fpfvg_interaction_count=0, first_presentation_flag=0.0, pd_array_strength=0.0, structural_importance=0.0, raw_json={'timestamp': '00:22:00', 'price': 23801.0, 'action': 'break', 'context': 'Asia_session_high_taken'})",
    "RichNodeFeature(time_minutes=28.0, daily_phase_sin=0.12186934340514748, daily_phase_cos=0.992546151641322, session_position=0.9655172413793104, time_to_close=1.0, weekend_proximity=0.2857142857142857, absolute_timestamp=1753916400, day_of_week=3, month_phase=1.0, normalized_price=0.237965, price_delta_1m=0.003061162990670088, price_delta_5m=0.0011366443315769784, price_delta_15m=0.0008591196409902529, volatility_window=0.012302985890196046, energy_state=0.0145, contamination_coefficient=0, fisher_regime=0, session_character=0, cross_tf_confluence=1.0, event_type_id=4, timeframe_source=0, liquidity_type=0, fpfvg_gap_size=0.0, fpfvg_interaction_count=0, first_presentation_flag=0.0, pd_array_strength=0.0, structural_importance=0.0, raw_json={'timestamp': '00:28:00', 'price': 23796.5, 'action': 'touch', 'context': 'Midnight_FPFVG_redelivered'})",
    "RichNodeFeature(time_minutes=30.0, daily_phase_sin=0.13052619222005157, daily_phase_cos=0.9914448613738104, session_position=1.0344827586206897, time_to_close=0, weekend_proximity=0.2857142857142857, absolute_timestamp=1753916400, day_of_week=3, month_phase=1.0, normalized_price=0.237835, price_delta_1m=0.0055765301803480235, price_delta_5m=-0.02224711080370025, price_delta_15m=0.011127155441943915, volatility_window=0.014779806045807913, energy_state=0.0145, contamination_coefficient=0, fisher_regime=0, session_character=0, cross_tf_confluence=1.0, event_type_id=4, timeframe_source=0, liquidity_type=0, fpfvg_gap_size=0.0, fpfvg_interaction_count=0, first_presentation_flag=0.0, pd_array_strength=0.0, structural_importance=0.0, raw_json={'timestamp': '00:30:00', 'price': 23783.5, 'action': 'touch', 'context': 'expansion_low_formation'})"
  ],
  "edges": {
    "temporal": [
      {
        "source": 0,
        "target": 4,
        "feature_idx": 0
      },
      {
        "source": 4,
        "target": 8,
        "feature_idx": 1
      },
      {
        "source": 8,
        "target": 9,
        "feature_idx": 2
      },
      {
        "source": 9,
        "target": 10,
        "feature_idx": 3
      },
      {
        "source": 10,
        "target": 11,
        "feature_idx": 4
      },
      {
        "source": 11,
        "target": 12,
        "feature_idx": 5
      },
      {
        "source": 12,
        "target": 3,
        "feature_idx": 6
      },
      {
        "source": 3,
        "target": 7,
        "feature_idx": 7
      },
      {
        "source": 7,
        "target": 13,
        "feature_idx": 8
      },
      {
        "source": 13,
        "target": 1,
        "feature_idx": 9
      },
      {
        "source": 1,
        "target": 5,
        "feature_idx": 10
      },
      {
        "source": 5,
        "target": 2,
        "feature_idx": 11
      },
      {
        "source": 2,
        "target": 6,
        "feature_idx": 12
      }
    ],
    "scale": [],
    "cascade": [],
    "pd_array": [],
    "cross_tf_confluence": [],
    "temporal_echo": [],
    "discovered": []
  },
  "rich_edge_features": [
    